{"cameraMode":{"drawMode":0,"name":"Shaded","section":"Shading Mode"},"sceneLighting":false,"audioPlay":false,"sceneViewState":{"showFog":true,"showMaterialUpdate":false,"showSkybox":false,"showFlares":true,"showImageEffects":true,"showParticleSystems":true},"in2DMode":false,"pivot":{"x":12.417708396911621,"y":-12.462494850158692,"z":-1.2768518924713135},"rotation":{"x":-0.13782013952732087,"y":0.02733176201581955,"z":-0.00378901488147676,"w":-0.9900964498519898},"size":10.187114715576172,"orthographic":false}